accoutrements/__init__.py
accoutrements/cmd/bugfix.py
accoutrements/cmd/chore.py
accoutrements/cmd/del.py
accoutrements/cmd/ditto.py
accoutrements/cmd/feature.py
accoutrements/cmd/master.py
accoutrements/cmd/rel.py
accoutrements/cmd/tidy.py
accoutrements/colours.py
accoutrements/config.py
accoutrements/versions.py
git_accoutrements-0.2.0.dist-info/entry_points.txt
git_accoutrements-0.2.0.dist-info/LICENSE
git_accoutrements-0.2.0.dist-info/WHEEL
git_accoutrements-0.2.0.dist-info/METADATA
git_accoutrements-0.2.0.dist-info/RECORD
