Metadata-Version: 2.1
Name: git-accoutrements
Version: 0.2.0
Summary: A collection of tools to help with a git based development workflow
Home-page: https://github.com/ejfitzgerald/git-accoutrements
License: MIT
Keywords: git,workflow,development
Author: Ed FitzGerald
Author-email: ejafitzgerald@gmail.com
Requires-Python: >=3.7,<4.0
Classifier: Development Status :: 3 - Alpha
Classifier: Intended Audience :: Developers
Classifier: License :: OSI Approved :: MIT License
Classifier: Programming Language :: Python :: 3
Classifier: Programming Language :: Python :: 3 :: Only
Classifier: Programming Language :: Python :: 3.10
Classifier: Programming Language :: Python :: 3.7
Classifier: Programming Language :: Python :: 3.8
Classifier: Programming Language :: Python :: 3.9
Requires-Dist: colored (>=1.4.3,<2.0.0)
Requires-Dist: toml (>=0.10.2,<0.11.0)
Project-URL: Bug Reports, https://github.com/ejfitzgerald/git-accoutrements/issues
Project-URL: Repository, https://github.com/ejfitzgerald/git-accoutrements
